prisma/__init__.py
prisma/__main__.py
prisma/_async_http.py
prisma/_compat.py
prisma/_config.py
prisma/_constants.py
prisma/_proxy.py
prisma/_raw_query.py
prisma/_sync_http.py
prisma/_types.py
prisma/errors.py
prisma/http_abstract.py
prisma/mypy.py
prisma/py.typed
prisma/testing.py
prisma/utils.py
prisma/validator.py
prisma/binaries/__init__.py
prisma/binaries/constants.py
prisma/binaries/platform.py
prisma/cli/__init__.py
prisma/cli/_node.py
prisma/cli/cli.py
prisma/cli/custom.py
prisma/cli/options.py
prisma/cli/prisma.py
prisma/cli/utils.py
prisma/cli/commands/__init__.py
prisma/cli/commands/dev.py
prisma/cli/commands/fetch.py
prisma/cli/commands/generate.py
prisma/cli/commands/version.py
prisma/engine/__init__.py
prisma/engine/errors.py
prisma/engine/utils.py
prisma/generator/__init__.py
prisma/generator/errors.py
prisma/generator/filters.py
prisma/generator/generator.py
prisma/generator/jsonrpc.py
prisma/generator/models.py
prisma/generator/schema.py
prisma/generator/types.py
prisma/generator/utils.py
prisma/generator/templates/_header.py.jinja
prisma/generator/templates/_utils.py.jinja
prisma/generator/templates/actions.py.jinja
prisma/generator/templates/bases.py.jinja
prisma/generator/templates/builder.py.jinja
prisma/generator/templates/client.py.jinja
prisma/generator/templates/enums.py.jinja
prisma/generator/templates/fields.py.jinja
prisma/generator/templates/http.py.jinja
prisma/generator/templates/models.py.jinja
prisma/generator/templates/partials.py.jinja
prisma/generator/templates/types.py.jinja
prisma/generator/templates/engine/abstract.py.jinja
prisma/generator/templates/engine/http.py.jinja
prisma/generator/templates/engine/query.py.jinja
prisma_cleanup/__init__.py
prisma_cleanup/__main__.py
prisma_cleanup/_cleanup.py
prisma_cleanup/py.typed
prisma_pynext-0.8.14.dist-info/LICENSE
prisma_pynext-0.8.14.dist-info/METADATA
prisma_pynext-0.8.14.dist-info/WHEEL
prisma_pynext-0.8.14.dist-info/entry_points.txt
prisma_pynext-0.8.14.dist-info/top_level.txt
prisma_pynext-0.8.14.dist-info/RECORD
