Metadata-Version: 2.1
Name: prisma-pynext
Version: 0.8.14
Summary: Prisma Client Python is an auto-generated and fully type-safe database client
Home-page: https://github.com/RobertCraigie/prisma-client-py
Author: Robert Craigie
Author-email: robert@craigie.dev
Maintainer: Filipe Sommer
License: APACHE
Project-URL: Documentation, https://prisma-client-py.readthedocs.io
Project-URL: Source, https://github.com/RobertCraigie/prisma-client-py
Project-URL: Tracker, https://github.com/RobertCraigie/prisma-client-py/issues
Keywords: orm,mysql,typing,prisma,sqlite,database,postgresql
Classifier: Development Status :: 4 - Beta
Classifier: Intended Audience :: Developers
Classifier: Typing :: Typed
Classifier: Topic :: Software Development :: Libraries :: Python Modules
Classifier: Topic :: Database :: Database Engines/Servers
Classifier: Topic :: Database :: Front-Ends
Classifier: License :: OSI Approved :: Apache Software License
Classifier: Programming Language :: Python :: 3.7
Classifier: Programming Language :: Python :: 3.8
Classifier: Programming Language :: Python :: 3.9
Classifier: Programming Language :: Python :: 3.10
Classifier: Programming Language :: Python :: 3.11
Classifier: Operating System :: POSIX
Classifier: Operating System :: MacOS
Classifier: Operating System :: POSIX :: Linux
Classifier: Operating System :: Microsoft :: Windows
Requires-Python: >=3.7.0
License-File: LICENSE
Requires-Dist: httpx (>=0.19.0)
Requires-Dist: jinja2 (>=2.11.2)
Requires-Dist: pydantic (>=1.8.0)
Requires-Dist: click (>=7.1.2)
Requires-Dist: python-dotenv (>=0.12.0)
Requires-Dist: typing-extensions (>=3.7)
Requires-Dist: tomlkit
Requires-Dist: nodeenv
Requires-Dist: cached-property ; python_version < "3.8"
Provides-Extra: all
Requires-Dist: nodejs-bin ; extra == 'all'
Provides-Extra: node
Requires-Dist: nodejs-bin ; extra == 'node'
